slasher/__init__.py
slasher/__main__.py
slasher/slasher.py
slasher/types.py
stream_slasher-2021.7.14.dist-info/WHEEL
stream_slasher-2021.7.14.dist-info/METADATA
stream_slasher-2021.7.14.dist-info/RECORD
