Metadata-Version: 2.1
Name: stream-slasher
Version: 2021.7.14
Summary: A commmand-line tool and Python library for autonomous editing of livestreams via live chat activity.
Home-page: https://github.com/SuperSonicHub1/Slasher
License: Unlicense
Author: Kyle Williams
Author-email: kyle.anthony.williams2@gmail.com
Requires-Python: >=3.7
Classifier: License :: Other/Proprietary License
Classifier: Programming Language :: Python :: 3
Classifier: Programming Language :: Python :: 3.10
Classifier: Programming Language :: Python :: 3.7
Classifier: Programming Language :: Python :: 3.8
Classifier: Programming Language :: Python :: 3.9
Classifier: Topic :: Multimedia :: Video
Requires-Dist: chat-downloader (==0.1.3)
Project-URL: Bug Tracker, https://github.com/SuperSonicHub1/Slasher/issues
Project-URL: Documentation, https://github.com/SuperSonicHub1/Slasher
Project-URL: Repository, https://github.com/SuperSonicHub1/Slasher
